quietaudit_sdk/__init__.py
quietaudit_sdk/client.py
quietaudit_sdk/config.py
quietaudit_sdk/exceptions.py
quietaudit_sdk/types.py
quietaudit_sdk/wrappers/__init__.py
quietaudit_sdk/wrappers/anthropic.py
quietaudit_sdk/wrappers/base.py
quietaudit_sdk/wrappers/openai.py
quietaudit_sdk-0.1.1.dist-info/licenses/LICENSE
quietaudit_sdk-0.1.1.dist-info/METADATA
quietaudit_sdk-0.1.1.dist-info/WHEEL
quietaudit_sdk-0.1.1.dist-info/top_level.txt
quietaudit_sdk-0.1.1.dist-info/RECORD
