Metadata-Version: 2.4
Name: quietaudit-sdk
Version: 0.1.1
Summary: Immutable audit trails for AI decisions
Home-page: https://github.com/quietstack/quietaudit-sdk
Author: QuietStack
Author-email: QuietStack <support@quietstack.ai>
License: MIT
Project-URL: Homepage, https://quietstack.ai
Project-URL: Documentation, https://quietstack.ai/docs
Project-URL: Repository, https://github.com/quietstack/quietaudit-sdk
Project-URL: Bug Reports, https://github.com/quietstack/quietaudit-sdk/issues
Keywords: ai,audit,blockchain,compliance,governance
Classifier: Development Status :: 3 - Alpha
Classifier: Intended Audience :: Developers
Classifier: Topic :: Software Development :: Libraries :: Python Modules
Classifier: Topic :: Scientific/Engineering :: Artificial Intelligence
Classifier: License :: OSI Approved :: MIT License
Classifier: Programming Language :: Python :: 3
Classifier: Programming Language :: Python :: 3.8
Classifier: Programming Language :: Python :: 3.9
Classifier: Programming Language :: Python :: 3.10
Classifier: Programming Language :: Python :: 3.11
Requires-Python: >=3.8
License-File: LICENSE
Requires-Dist: httpx>=0.24.0
Provides-Extra: dev
Requires-Dist: pytest>=6.0; extra == "dev"
Requires-Dist: pytest-asyncio; extra == "dev"
Requires-Dist: black; extra == "dev"
Requires-Dist: flake8; extra == "dev"
Requires-Dist: mypy; extra == "dev"
Provides-Extra: openai
Requires-Dist: openai>=1.0.0; extra == "openai"
Provides-Extra: anthropic
Requires-Dist: anthropic>=0.3.0; extra == "anthropic"
Dynamic: author
Dynamic: home-page
Dynamic: license-file
Dynamic: requires-python
